<?xml version="1.0"?>
<blend_map_tileinfo xmlns:xsd="http://www.w3.org/2001/XMLSchema" xmlns:xsi="http://www.w3.org/2001/XMLSchema-instance" blend_weight="0.9" need_tex_file="1">
  <tile_tex tex_id="16" scale_x="2" scale_y="2" rotate="0" />
  <tile_tex tex_id="30" scale_x="5" scale_y="5" rotate="0" />
  <tile_tex tex_id="35" scale_x="1" scale_y="1" rotate="0" />
  <tile_obj obj_id="193220" obj_type="0" tileset_id="test_tile_water15B" layer_index="24" pos_x="-3872" pos_y="-480" offset_z="0" arg_x="1" arg_y="1" arg_z="0" visible="1" is_locked="0" x_flip="0" obj_infos="" />
  <tile_obj obj_id="193272" obj_type="0" tileset_id="test_tile_water15B" layer_index="24" pos_x="-3904" pos_y="-496" offset_z="0" arg_x="1" arg_y="1" arg_z="0" visible="1" is_locked="0" x_flip="0" obj_infos="" />
  <tile_obj obj_id="193281" obj_type="0" tileset_id="test_tile_water04" layer_index="24" pos_x="-4000" pos_y="-544" offset_z="0" arg_x="1" arg_y="1" arg_z="0" visible="1" is_locked="0" x_flip="0" obj_infos="" />
  <tile_obj obj_id="193280" obj_type="0" tileset_id="test_tile_water12B" layer_index="24" pos_x="-3968" pos_y="-528" offset_z="0" arg_x="1" arg_y="1" arg_z="0" visible="1" is_locked="0" x_flip="0" obj_infos="" />
  <tile_obj obj_id="193275" obj_type="0" tileset_id="test_tile_water04" layer_index="24" pos_x="-3968" pos_y="-496" offset_z="0" arg_x="1" arg_y="1" arg_z="0" visible="1" is_locked="0" x_flip="0" obj_infos="" />
  <tile_obj obj_id="193279" obj_type="0" tileset_id="test_tile_water08" layer_index="24" pos_x="-3936" pos_y="-512" offset_z="0" arg_x="1" arg_y="1" arg_z="0" visible="1" is_locked="0" x_flip="0" obj_infos="" />
  <tile_obj obj_id="193274" obj_type="0" tileset_id="test_tile_water12" layer_index="24" pos_x="-3936" pos_y="-480" offset_z="0" arg_x="1" arg_y="1" arg_z="0" visible="1" is_locked="0" x_flip="0" obj_infos="" />
  <tile_obj obj_id="190886" obj_type="0" tileset_id="test_tile_water15B" layer_index="24" pos_x="-3648" pos_y="-496" offset_z="0" arg_x="1" arg_y="1" arg_z="0" visible="1" is_locked="0" x_flip="0" obj_infos="" />
  <tile_obj obj_id="189925" obj_type="0" tileset_id="test_tile_water15B" layer_index="24" pos_x="-3616" pos_y="-512" offset_z="0" arg_x="1" arg_y="1" arg_z="0" visible="1" is_locked="0" x_flip="0" obj_infos="" />
  <tile_obj obj_id="191432" obj_type="0" tileset_id="test_tile_water15" layer_index="24" pos_x="-3840" pos_y="-528" offset_z="0" arg_x="1" arg_y="1" arg_z="0" visible="1" is_locked="0" x_flip="0" obj_infos="" />
  <tile_obj obj_id="191461" obj_type="0" tileset_id="test_tile_water15B" layer_index="24" pos_x="-3808" pos_y="-480" offset_z="0" arg_x="1" arg_y="1" arg_z="0" visible="1" is_locked="0" x_flip="0" obj_infos="" />
  <tile_obj obj_id="193268" obj_type="0" tileset_id="test_tile_water15" layer_index="24" pos_x="-3872" pos_y="-512" offset_z="0" arg_x="1" arg_y="1" arg_z="0" visible="1" is_locked="0" x_flip="0" obj_infos="" />
  <tile_obj obj_id="191427" obj_type="0" tileset_id="test_tile_water15B" layer_index="24" pos_x="-3872" pos_y="-544" offset_z="0" arg_x="1" arg_y="1" arg_z="0" visible="1" is_locked="0" x_flip="0" obj_infos="" />
  <tile_obj obj_id="191467" obj_type="0" tileset_id="test_tile_water15" layer_index="24" pos_x="-3840" pos_y="-496" offset_z="0" arg_x="1" arg_y="1" arg_z="0" visible="1" is_locked="0" x_flip="0" obj_infos="" />
  <tile_obj obj_id="189838" obj_type="0" tileset_id="test_tile_water15B" layer_index="24" pos_x="-3616" pos_y="-544" offset_z="0" arg_x="1" arg_y="1" arg_z="0" visible="1" is_locked="0" x_flip="0" obj_infos="" />
  <tile_obj obj_id="189926" obj_type="0" tileset_id="test_tile_water15" layer_index="24" pos_x="-3584" pos_y="-528" offset_z="0" arg_x="1" arg_y="1" arg_z="0" visible="1" is_locked="0" x_flip="0" obj_infos="" />
  <tile_obj obj_id="189927" obj_type="0" tileset_id="test_tile_water06" layer_index="24" pos_x="-3552" pos_y="-512" offset_z="0" arg_x="1" arg_y="1" arg_z="0" visible="1" is_locked="0" x_flip="0" obj_infos="" />
  <tile_obj obj_id="182383" obj_type="0" tileset_id="test_tile_water15B" layer_index="24" pos_x="-3552" pos_y="-544" offset_z="0" arg_x="1" arg_y="1" arg_z="0" visible="1" is_locked="0" x_flip="0" obj_infos="" />
  <tile_obj obj_id="189929" obj_type="0" tileset_id="test_tile_water15B" layer_index="24" pos_x="-3552" pos_y="-480" offset_z="0" arg_x="1" arg_y="1" arg_z="0" visible="1" is_locked="0" x_flip="0" obj_infos="" />
  <tile_obj obj_id="189924" obj_type="0" tileset_id="test_tile_water15B" layer_index="24" pos_x="-3584" pos_y="-496" offset_z="0" arg_x="1" arg_y="1" arg_z="0" visible="1" is_locked="0" x_flip="0" obj_infos="" />
  <tile_obj obj_id="189843" obj_type="0" tileset_id="test_tile_water15" layer_index="24" pos_x="-3616" pos_y="-480" offset_z="0" arg_x="1" arg_y="1" arg_z="0" visible="1" is_locked="0" x_flip="0" obj_infos="" />
  <tile_obj obj_id="190883" obj_type="0" tileset_id="test_tile_water15B" layer_index="24" pos_x="-3680" pos_y="-480" offset_z="0" arg_x="1" arg_y="1" arg_z="0" visible="1" is_locked="0" x_flip="0" obj_infos="" />
  <tile_obj obj_id="189835" obj_type="0" tileset_id="test_tile_water15" layer_index="24" pos_x="-3648" pos_y="-528" offset_z="0" arg_x="1" arg_y="1" arg_z="0" visible="1" is_locked="0" x_flip="0" obj_infos="" />
  <tile_obj obj_id="190863" obj_type="0" tileset_id="test_tile_water15" layer_index="24" pos_x="-3680" pos_y="-544" offset_z="0" arg_x="1" arg_y="1" arg_z="0" visible="1" is_locked="0" x_flip="0" obj_infos="" />
  <tile_obj obj_id="193278" obj_type="0" tileset_id="test_tile_water15B" layer_index="24" pos_x="-3904" pos_y="-528" offset_z="0" arg_x="1" arg_y="1" arg_z="0" visible="1" is_locked="0" x_flip="0" obj_infos="" />
  <tile_obj obj_id="193276" obj_type="0" tileset_id="test_tile_water15B" layer_index="24" pos_x="-3936" pos_y="-544" offset_z="0" arg_x="1" arg_y="1" arg_z="0" visible="1" is_locked="0" x_flip="0" obj_infos="" />
  <tile_obj obj_id="191431" obj_type="0" tileset_id="test_tile_water15B" layer_index="24" pos_x="-3808" pos_y="-544" offset_z="0" arg_x="1" arg_y="1" arg_z="0" visible="1" is_locked="0" x_flip="0" obj_infos="" />
  <tile_obj obj_id="191421" obj_type="0" tileset_id="test_tile_water15B" layer_index="24" pos_x="-3808" pos_y="-512" offset_z="0" arg_x="1" arg_y="1" arg_z="0" visible="1" is_locked="0" x_flip="0" obj_infos="" />
  <tile_obj obj_id="191423" obj_type="0" tileset_id="test_tile_water15B" layer_index="24" pos_x="-3776" pos_y="-496" offset_z="0" arg_x="1" arg_y="1" arg_z="0" visible="1" is_locked="0" x_flip="0" obj_infos="" />
  <tile_obj obj_id="191417" obj_type="0" tileset_id="test_tile_water15" layer_index="24" pos_x="-3744" pos_y="-480" offset_z="0" arg_x="1" arg_y="1" arg_z="0" visible="1" is_locked="0" x_flip="0" obj_infos="" />
  <tile_obj obj_id="190884" obj_type="0" tileset_id="test_tile_water15B" layer_index="24" pos_x="-3712" pos_y="-496" offset_z="0" arg_x="1" arg_y="1" arg_z="0" visible="1" is_locked="0" x_flip="0" obj_infos="" />
  <tile_obj obj_id="190885" obj_type="0" tileset_id="test_tile_water15" layer_index="24" pos_x="-3680" pos_y="-512" offset_z="0" arg_x="1" arg_y="1" arg_z="0" visible="1" is_locked="0" x_flip="0" obj_infos="" />
  <tile_obj obj_id="181476" obj_type="0" tileset_id="test_tile_water15B" layer_index="24" pos_x="-3712" pos_y="-528" offset_z="0" arg_x="1" arg_y="1" arg_z="0" visible="1" is_locked="0" x_flip="0" obj_infos="" />
  <tile_obj obj_id="181477" obj_type="0" tileset_id="test_tile_water15B" layer_index="24" pos_x="-3744" pos_y="-544" offset_z="0" arg_x="1" arg_y="1" arg_z="0" visible="1" is_locked="0" x_flip="0" obj_infos="" />
  <tile_obj obj_id="189823" obj_type="0" tileset_id="test_tile_water15B" layer_index="24" pos_x="-3776" pos_y="-528" offset_z="0" arg_x="1" arg_y="1" arg_z="0" visible="1" is_locked="0" x_flip="0" obj_infos="" />
  <tile_obj obj_id="180512" obj_type="0" tileset_id="test_tile_water15B" layer_index="24" pos_x="-3744" pos_y="-512" offset_z="0" arg_x="1" arg_y="1" arg_z="0" visible="1" is_locked="0" x_flip="0" obj_infos="" />
  <tile_obj obj_id="193222" obj_type="0" tileset_id="test_tile_water15B" layer_index="24" pos_x="-3840" pos_y="-464" offset_z="0" arg_x="1" arg_y="1" arg_z="0" visible="1" is_locked="0" x_flip="0" obj_infos="" />
  <tile_obj obj_id="198703" obj_type="0" tileset_id="test_tile_water04" layer_index="24" pos_x="-3616" pos_y="-160" offset_z="0" arg_x="1" arg_y="1" arg_z="0" visible="1" is_locked="0" x_flip="0" obj_infos="" />
  <tile_obj obj_id="198702" obj_type="0" tileset_id="test_tile_water12" layer_index="24" pos_x="-3584" pos_y="-144" offset_z="0" arg_x="1" arg_y="1" arg_z="0" visible="1" is_locked="0" x_flip="0" obj_infos="" />
  <tile_obj obj_id="198695" obj_type="0" tileset_id="test_tile_water04" layer_index="24" pos_x="-3584" pos_y="-112" offset_z="0" arg_x="1" arg_y="1" arg_z="0" visible="1" is_locked="0" x_flip="0" obj_infos="" />
  <tile_obj obj_id="193224" obj_type="0" tileset_id="test_tile_water12" layer_index="24" pos_x="-3904" pos_y="-464" offset_z="0" arg_x="1" arg_y="1" arg_z="0" visible="1" is_locked="0" x_flip="0" obj_infos="" />
  <tile_obj obj_id="193219" obj_type="0" tileset_id="test_tile_water04" layer_index="24" pos_x="-3872" pos_y="-416" offset_z="0" arg_x="1" arg_y="1" arg_z="0" visible="1" is_locked="0" x_flip="0" obj_infos="" />
  <tile_obj obj_id="193215" obj_type="0" tileset_id="test_tile_water04" layer_index="24" pos_x="-3808" pos_y="-352" offset_z="0" arg_x="1" arg_y="1" arg_z="0" visible="1" is_locked="0" x_flip="0" obj_infos="" />
  <tile_obj obj_id="193214" obj_type="0" tileset_id="test_tile_water12B" layer_index="24" pos_x="-3776" pos_y="-336" offset_z="0" arg_x="1" arg_y="1" arg_z="0" visible="1" is_locked="0" x_flip="0" obj_infos="" />
  <tile_obj obj_id="193223" obj_type="0" tileset_id="test_tile_water12" layer_index="24" pos_x="-3872" pos_y="-448" offset_z="0" arg_x="1" arg_y="1" arg_z="0" visible="1" is_locked="0" x_flip="0" obj_infos="" />
  <tile_obj obj_id="193217" obj_type="0" tileset_id="test_tile_water08" layer_index="24" pos_x="-3840" pos_y="-432" offset_z="0" arg_x="1" arg_y="1" arg_z="0" visible="1" is_locked="0" x_flip="0" obj_infos="" />
  <tile_obj obj_id="193185" obj_type="0" tileset_id="test_tile_water04" layer_index="24" pos_x="-3712" pos_y="-272" offset_z="0" arg_x="1" arg_y="1" arg_z="0" visible="1" is_locked="0" x_flip="0" obj_infos="" />
  <tile_obj obj_id="193184" obj_type="0" tileset_id="test_tile_water12B" layer_index="24" pos_x="-3680" pos_y="-256" offset_z="0" arg_x="1" arg_y="1" arg_z="0" visible="1" is_locked="0" x_flip="0" obj_infos="" />
  <tile_obj obj_id="193189" obj_type="0" tileset_id="test_tile_water12B" layer_index="24" pos_x="-3648" pos_y="-240" offset_z="0" arg_x="1" arg_y="1" arg_z="0" visible="1" is_locked="0" x_flip="0" obj_infos="" />
  <tile_obj obj_id="198698" obj_type="0" tileset_id="test_tile_water08" layer_index="24" pos_x="-3552" pos_y="-128" offset_z="0" arg_x="1" arg_y="1" arg_z="0" visible="1" is_locked="0" x_flip="0" obj_infos="" />
  <tile_obj obj_id="198694" obj_type="0" tileset_id="test_tile_water12" layer_index="24" pos_x="-3552" pos_y="-96" offset_z="0" arg_x="1" arg_y="1" arg_z="0" visible="1" is_locked="0" x_flip="0" obj_infos="" />
  <tile_obj obj_id="192478" obj_type="0" tileset_id="test_tile_water04" layer_index="24" pos_x="-3648" pos_y="-208" offset_z="0" arg_x="1" arg_y="1" arg_z="0" visible="1" is_locked="0" x_flip="0" obj_infos="" />
  <tile_obj obj_id="192477" obj_type="0" tileset_id="test_tile_water12B" layer_index="24" pos_x="-3616" pos_y="-192" offset_z="0" arg_x="1" arg_y="1" arg_z="0" visible="1" is_locked="0" x_flip="0" obj_infos="" />
  <tile_obj obj_id="198701" obj_type="0" tileset_id="test_tile_water08" layer_index="24" pos_x="-3584" pos_y="-176" offset_z="0" arg_x="1" arg_y="1" arg_z="0" visible="1" is_locked="0" x_flip="0" obj_infos="" />
  <tile_obj obj_id="193213" obj_type="0" tileset_id="test_tile_water12" layer_index="24" pos_x="-3744" pos_y="-320" offset_z="0" arg_x="1" arg_y="1" arg_z="0" visible="1" is_locked="0" x_flip="0" obj_infos="" />
  <tile_obj obj_id="192471" obj_type="0" tileset_id="test_tile_water12" layer_index="24" pos_x="-3712" pos_y="-304" offset_z="0" arg_x="1" arg_y="1" arg_z="0" visible="1" is_locked="0" x_flip="0" obj_infos="" />
  <tile_obj obj_id="193181" obj_type="0" tileset_id="test_tile_water08" layer_index="24" pos_x="-3680" pos_y="-288" offset_z="0" arg_x="1" arg_y="1" arg_z="0" visible="1" is_locked="0" x_flip="0" obj_infos="" />
  <tile_obj obj_id="193188" obj_type="0" tileset_id="test_tile_water08" layer_index="24" pos_x="-3616" pos_y="-224" offset_z="0" arg_x="1" arg_y="1" arg_z="0" visible="1" is_locked="0" x_flip="0" obj_infos="" />
  <tile_obj obj_id="192473" obj_type="0" tileset_id="test_tile_water15B" layer_index="24" pos_x="-3584" pos_y="-208" offset_z="0" arg_x="1" arg_y="1" arg_z="0" visible="1" is_locked="0" x_flip="0" obj_infos="" />
  <tile_obj obj_id="193180" obj_type="0" tileset_id="test_tile_water15B" layer_index="24" pos_x="-3648" pos_y="-272" offset_z="0" arg_x="1" arg_y="1" arg_z="0" visible="1" is_locked="0" x_flip="0" obj_infos="" />
  <tile_obj obj_id="193186" obj_type="0" tileset_id="test_tile_water15B" layer_index="24" pos_x="-3616" pos_y="-256" offset_z="0" arg_x="1" arg_y="1" arg_z="0" visible="1" is_locked="0" x_flip="0" obj_infos="" />
  <tile_obj obj_id="193172" obj_type="0" tileset_id="test_tile_water15B" layer_index="24" pos_x="-3552" pos_y="-192" offset_z="0" arg_x="1" arg_y="1" arg_z="0" visible="1" is_locked="0" x_flip="0" obj_infos="" />
  <tile_obj obj_id="193210" obj_type="0" tileset_id="test_tile_water15" layer_index="24" pos_x="-3744" pos_y="-352" offset_z="0" arg_x="1" arg_y="1" arg_z="0" visible="1" is_locked="0" x_flip="0" obj_infos="" />
  <tile_obj obj_id="189783" obj_type="0" tileset_id="test_tile_water15" layer_index="24" pos_x="-3712" pos_y="-368" offset_z="0" arg_x="1" arg_y="1" arg_z="0" visible="1" is_locked="0" x_flip="0" obj_infos="" />
  <tile_obj obj_id="193218" obj_type="0" tileset_id="test_tile_water12" layer_index="24" pos_x="-3840" pos_y="-400" offset_z="0" arg_x="1" arg_y="1" arg_z="0" visible="1" is_locked="0" x_flip="0" obj_infos="" />
  <tile_obj obj_id="189781" obj_type="0" tileset_id="test_tile_water12" layer_index="24" pos_x="-3808" pos_y="-384" offset_z="0" arg_x="1" arg_y="1" arg_z="0" visible="1" is_locked="0" x_flip="0" obj_infos="" />
  <tile_obj obj_id="193211" obj_type="0" tileset_id="test_tile_water08" layer_index="24" pos_x="-3776" pos_y="-368" offset_z="0" arg_x="1" arg_y="1" arg_z="0" visible="1" is_locked="0" x_flip="0" obj_infos="" />
  <tile_obj obj_id="189784" obj_type="0" tileset_id="test_tile_water15B" layer_index="24" pos_x="-3744" pos_y="-384" offset_z="0" arg_x="1" arg_y="1" arg_z="0" visible="1" is_locked="0" x_flip="0" obj_infos="" />
  <tile_obj obj_id="191403" obj_type="0" tileset_id="test_tile_water15" layer_index="24" pos_x="-3744" pos_y="-416" offset_z="0" arg_x="1" arg_y="1" arg_z="0" visible="1" is_locked="0" x_flip="0" obj_infos="" />
  <tile_obj obj_id="193192" obj_type="0" tileset_id="test_tile_water15" layer_index="24" pos_x="-3776" pos_y="-432" offset_z="0" arg_x="1" arg_y="1" arg_z="0" visible="1" is_locked="0" x_flip="0" obj_infos="" />
  <tile_obj obj_id="193216" obj_type="0" tileset_id="test_tile_water15B" layer_index="24" pos_x="-3808" pos_y="-416" offset_z="0" arg_x="1" arg_y="1" arg_z="0" visible="1" is_locked="0" x_flip="0" obj_infos="" />
  <tile_obj obj_id="189774" obj_type="0" tileset_id="test_tile_water15" layer_index="24" pos_x="-3776" pos_y="-400" offset_z="0" arg_x="1" arg_y="1" arg_z="0" visible="1" is_locked="0" x_flip="0" obj_infos="" />
  <tile_obj obj_id="193212" obj_type="0" tileset_id="test_tile_water15B" layer_index="24" pos_x="-3712" pos_y="-336" offset_z="0" arg_x="1" arg_y="1" arg_z="0" visible="1" is_locked="0" x_flip="0" obj_infos="" />
  <tile_obj obj_id="189788" obj_type="0" tileset_id="test_tile_water15" layer_index="24" pos_x="-3680" pos_y="-352" offset_z="0" arg_x="1" arg_y="1" arg_z="0" visible="1" is_locked="0" x_flip="0" obj_infos="" />
  <tile_obj obj_id="192421" obj_type="0" tileset_id="test_tile_water15" layer_index="24" pos_x="-3584" pos_y="-272" offset_z="0" arg_x="1" arg_y="1" arg_z="0" visible="1" is_locked="0" x_flip="0" obj_infos="" />
  <tile_obj obj_id="189792" obj_type="0" tileset_id="test_tile_water15B" layer_index="24" pos_x="-3552" pos_y="-288" offset_z="0" arg_x="1" arg_y="1" arg_z="0" visible="1" is_locked="0" x_flip="0" obj_infos="" />
  <tile_obj obj_id="193190" obj_type="0" tileset_id="test_tile_water15B" layer_index="24" pos_x="-3808" pos_y="-448" offset_z="0" arg_x="1" arg_y="1" arg_z="0" visible="1" is_locked="0" x_flip="0" obj_infos="" />
  <tile_obj obj_id="191463" obj_type="0" tileset_id="test_tile_water15" layer_index="24" pos_x="-3776" pos_y="-464" offset_z="0" arg_x="1" arg_y="1" arg_z="0" visible="1" is_locked="0" x_flip="0" obj_infos="" />
  <tile_obj obj_id="190842" obj_type="0" tileset_id="test_tile_water15B" layer_index="24" pos_x="-3552" pos_y="-416" offset_z="0" arg_x="1" arg_y="1" arg_z="0" visible="1" is_locked="0" x_flip="0" obj_infos="" />
  <tile_obj obj_id="191959" obj_type="0" tileset_id="test_tile_water15B" layer_index="24" pos_x="-3584" pos_y="-432" offset_z="0" arg_x="1" arg_y="1" arg_z="0" visible="1" is_locked="0" x_flip="0" obj_infos="" />
  <tile_obj obj_id="189310" obj_type="0" tileset_id="test_tile_water15" layer_index="24" pos_x="-3552" pos_y="-448" offset_z="0" arg_x="1" arg_y="1" arg_z="0" visible="1" is_locked="0" x_flip="0" obj_infos="" />
  <tile_obj obj_id="181500" obj_type="0" tileset_id="test_tile_water15B" layer_index="24" pos_x="-3584" pos_y="-464" offset_z="0" arg_x="1" arg_y="1" arg_z="0" visible="1" is_locked="0" x_flip="0" obj_infos="" />
  <tile_obj obj_id="190834" obj_type="0" tileset_id="test_tile_water15B" layer_index="24" pos_x="-3552" pos_y="-352" offset_z="0" arg_x="1" arg_y="1" arg_z="0" visible="1" is_locked="0" x_flip="0" obj_infos="" />
  <tile_obj obj_id="190844" obj_type="0" tileset_id="test_tile_water15" layer_index="24" pos_x="-3552" pos_y="-384" offset_z="0" arg_x="1" arg_y="1" arg_z="0" visible="1" is_locked="0" x_flip="0" obj_infos="" />
  <tile_obj obj_id="181491" obj_type="0" tileset_id="test_tile_water15" layer_index="24" pos_x="-3584" pos_y="-368" offset_z="0" arg_x="1" arg_y="1" arg_z="0" visible="1" is_locked="0" x_flip="0" obj_infos="" />
  <tile_obj obj_id="191405" obj_type="0" tileset_id="test_tile_water15" layer_index="24" pos_x="-3744" pos_y="-448" offset_z="0" arg_x="1" arg_y="1" arg_z="0" visible="1" is_locked="0" x_flip="0" obj_infos="" />
  <tile_obj obj_id="191401" obj_type="0" tileset_id="test_tile_water15" layer_index="24" pos_x="-3712" pos_y="-432" offset_z="0" arg_x="1" arg_y="1" arg_z="0" visible="1" is_locked="0" x_flip="0" obj_infos="" />
  <tile_obj obj_id="191958" obj_type="0" tileset_id="test_tile_water15B" layer_index="24" pos_x="-3616" pos_y="-448" offset_z="0" arg_x="1" arg_y="1" arg_z="0" visible="1" is_locked="0" x_flip="0" obj_infos="" />
  <tile_obj obj_id="189847" obj_type="0" tileset_id="test_tile_water15" layer_index="24" pos_x="-3648" pos_y="-464" offset_z="0" arg_x="1" arg_y="1" arg_z="0" visible="1" is_locked="0" x_flip="0" obj_infos="" />
  <tile_obj obj_id="191408" obj_type="0" tileset_id="test_tile_water15" layer_index="24" pos_x="-3712" pos_y="-464" offset_z="0" arg_x="1" arg_y="1" arg_z="0" visible="1" is_locked="0" x_flip="0" obj_infos="" />
  <tile_obj obj_id="181482" obj_type="0" tileset_id="test_tile_water15" layer_index="24" pos_x="-3680" pos_y="-448" offset_z="0" arg_x="1" arg_y="1" arg_z="0" visible="1" is_locked="0" x_flip="0" obj_infos="" />
  <tile_obj obj_id="189855" obj_type="0" tileset_id="test_tile_water15B" layer_index="24" pos_x="-3712" pos_y="-400" offset_z="0" arg_x="1" arg_y="1" arg_z="0" visible="1" is_locked="0" x_flip="0" obj_infos="" />
  <tile_obj obj_id="189786" obj_type="0" tileset_id="test_tile_water15" layer_index="24" pos_x="-3680" pos_y="-384" offset_z="0" arg_x="1" arg_y="1" arg_z="0" visible="1" is_locked="0" x_flip="0" obj_infos="" />
  <tile_obj obj_id="189787" obj_type="0" tileset_id="test_tile_water15B" layer_index="24" pos_x="-3648" pos_y="-368" offset_z="0" arg_x="1" arg_y="1" arg_z="0" visible="1" is_locked="0" x_flip="0" obj_infos="" />
  <tile_obj obj_id="181492" obj_type="0" tileset_id="test_tile_water15" layer_index="24" pos_x="-3616" pos_y="-384" offset_z="0" arg_x="1" arg_y="1" arg_z="0" visible="1" is_locked="0" x_flip="0" obj_infos="" />
  <tile_obj obj_id="190839" obj_type="0" tileset_id="test_tile_water15" layer_index="24" pos_x="-3584" pos_y="-400" offset_z="0" arg_x="1" arg_y="1" arg_z="0" visible="1" is_locked="0" x_flip="0" obj_infos="" />
  <tile_obj obj_id="191960" obj_type="0" tileset_id="test_tile_water15" layer_index="24" pos_x="-3616" pos_y="-416" offset_z="0" arg_x="1" arg_y="1" arg_z="0" visible="1" is_locked="0" x_flip="0" obj_infos="" />
  <tile_obj obj_id="191961" obj_type="0" tileset_id="test_tile_water15B" layer_index="24" pos_x="-3648" pos_y="-432" offset_z="0" arg_x="1" arg_y="1" arg_z="0" visible="1" is_locked="0" x_flip="0" obj_infos="" />
  <tile_obj obj_id="189853" obj_type="0" tileset_id="test_tile_water15" layer_index="24" pos_x="-3680" pos_y="-416" offset_z="0" arg_x="1" arg_y="1" arg_z="0" visible="1" is_locked="0" x_flip="0" obj_infos="" />
  <tile_obj obj_id="180503" obj_type="0" tileset_id="test_tile_water15" layer_index="24" pos_x="-3648" pos_y="-400" offset_z="0" arg_x="1" arg_y="1" arg_z="0" visible="1" is_locked="0" x_flip="0" obj_infos="" />
  <tile_obj obj_id="192467" obj_type="0" tileset_id="test_tile_water15B" layer_index="24" pos_x="-3680" pos_y="-320" offset_z="0" arg_x="1" arg_y="1" arg_z="0" visible="1" is_locked="0" x_flip="0" obj_infos="" />
  <tile_obj obj_id="193177" obj_type="0" tileset_id="test_tile_water15B" layer_index="24" pos_x="-3648" pos_y="-304" offset_z="0" arg_x="1" arg_y="1" arg_z="0" visible="1" is_locked="0" x_flip="0" obj_infos="" />
  <tile_obj obj_id="193176" obj_type="0" tileset_id="test_tile_water15B" layer_index="24" pos_x="-3616" pos_y="-288" offset_z="0" arg_x="1" arg_y="1" arg_z="0" visible="1" is_locked="0" x_flip="0" obj_infos="" />
  <tile_obj obj_id="189793" obj_type="0" tileset_id="test_tile_water15" layer_index="24" pos_x="-3584" pos_y="-304" offset_z="0" arg_x="1" arg_y="1" arg_z="0" visible="1" is_locked="0" x_flip="0" obj_infos="" />
  <tile_obj obj_id="190837" obj_type="0" tileset_id="test_tile_water15" layer_index="24" pos_x="-3552" pos_y="-320" offset_z="0" arg_x="1" arg_y="1" arg_z="0" visible="1" is_locked="0" x_flip="0" obj_infos="" />
  <tile_obj obj_id="190838" obj_type="0" tileset_id="test_tile_water15" layer_index="24" pos_x="-3584" pos_y="-336" offset_z="0" arg_x="1" arg_y="1" arg_z="0" visible="1" is_locked="0" x_flip="0" obj_infos="" />
  <tile_obj obj_id="189771" obj_type="0" tileset_id="test_tile_water15B" layer_index="24" pos_x="-3616" pos_y="-352" offset_z="0" arg_x="1" arg_y="1" arg_z="0" visible="1" is_locked="0" x_flip="0" obj_infos="" />
  <tile_obj obj_id="189768" obj_type="0" tileset_id="test_tile_water15B" layer_index="24" pos_x="-3648" pos_y="-336" offset_z="0" arg_x="1" arg_y="1" arg_z="0" visible="1" is_locked="0" x_flip="0" obj_infos="" />
  <tile_obj obj_id="180494" obj_type="0" tileset_id="test_tile_water15" layer_index="24" pos_x="-3616" pos_y="-320" offset_z="0" arg_x="1" arg_y="1" arg_z="0" visible="1" is_locked="0" x_flip="0" obj_infos="" />
  <tile_obj obj_id="193187" obj_type="0" tileset_id="test_tile_water15B" layer_index="24" pos_x="-3584" pos_y="-240" offset_z="0" arg_x="1" arg_y="1" arg_z="0" visible="1" is_locked="0" x_flip="0" obj_infos="" />
  <tile_obj obj_id="192446" obj_type="0" tileset_id="test_tile_water15" layer_index="24" pos_x="-3552" pos_y="-224" offset_z="0" arg_x="1" arg_y="1" arg_z="0" visible="1" is_locked="0" x_flip="0" obj_infos="" />
  <tile_obj obj_id="192417" obj_type="0" tileset_id="test_tile_water15B" layer_index="24" pos_x="-3552" pos_y="-256" offset_z="0" arg_x="1" arg_y="1" arg_z="0" visible="1" is_locked="0" x_flip="0" obj_infos="" />
  <tile_obj obj_id="198700" obj_type="0" tileset_id="test_tile_water15B" layer_index="24" pos_x="-3552" pos_y="-160" offset_z="0" arg_x="1" arg_y="1" arg_z="0" visible="1" is_locked="0" x_flip="0" obj_infos="" />
  <tile_obj obj_id="249920" obj_type="0" tileset_id="BRF_yanti02" layer_index="36" pos_x="-4672.308" pos_y="178.944061" offset_z="0" arg_x="1" arg_y="1" arg_z="0" visible="1" is_locked="0" x_flip="1" obj_infos="" bind_tag="" control_info="" />
  <tile_obj obj_id="262602" obj_type="0" tileset_id="BRF_rock05" layer_index="36" pos_x="-4515.573" pos_y="477.704132" offset_z="0" arg_x="1" arg_y="1" arg_z="0" visible="1" is_locked="0" x_flip="0" obj_infos="" bind_tag="" control_info="" />
  <tile_obj obj_id="262674" obj_type="0" tileset_id="BRF_tree05" layer_index="22" pos_x="-4625.79541" pos_y="517.7041" offset_z="0" arg_x="1" arg_y="1" arg_z="0" visible="1" is_locked="0" x_flip="0" obj_infos="" bind_tag="" control_info="" />
  <tile_obj obj_id="262689" obj_type="0" tileset_id="BRF_grass02" layer_index="31" pos_x="-4525.35059" pos_y="542.8152" offset_z="0" arg_x="1" arg_y="1" arg_z="0" visible="1" is_locked="0" x_flip="0" obj_infos="" bind_tag="" control_info="" />
  <tile_obj obj_id="262690" obj_type="0" tileset_id="BRF_grass02" layer_index="31" pos_x="-4669.79541" pos_y="539.481934" offset_z="0" arg_x="1" arg_y="1" arg_z="0" visible="1" is_locked="0" x_flip="0" obj_infos="" bind_tag="" control_info="" />
  <tile_obj obj_id="262705" obj_type="0" tileset_id="BRF_rock06" layer_index="23" pos_x="-4598.462" pos_y="403.037445" offset_z="0" arg_x="1" arg_y="1" arg_z="0" visible="1" is_locked="0" x_flip="0" obj_infos="" bind_tag="" control_info="" />
  <tile_obj obj_id="262713" obj_type="0" tileset_id="BRF_tree02" layer_index="22" pos_x="-4533.91064" pos_y="551.6039" offset_z="0" arg_x="1" arg_y="1" arg_z="0" visible="1" is_locked="0" x_flip="0" obj_infos="" bind_tag="" control_info="" />
  <tile_obj obj_id="262714" obj_type="0" tileset_id="BRF_tree03" layer_index="22" pos_x="-4491.39258" pos_y="442.54834" offset_z="0" arg_x="1" arg_y="1" arg_z="0" visible="1" is_locked="0" x_flip="0" obj_infos="" bind_tag="" control_info="" />
  <tile_obj obj_id="262715" obj_type="0" tileset_id="BRF_tree01" layer_index="22" pos_x="-4653.689" pos_y="190.696487" offset_z="0" arg_x="1" arg_y="1" arg_z="0" visible="1" is_locked="0" x_flip="0" obj_infos="" bind_tag="" control_info="" />
  <tile_obj obj_id="262716" obj_type="0" tileset_id="BRF_tree01" layer_index="22" pos_x="-4598.72559" pos_y="379.659424" offset_z="0" arg_x="1" arg_y="1" arg_z="0" visible="1" is_locked="0" x_flip="0" obj_infos="" bind_tag="" control_info="" />
  <tile_obj obj_id="262717" obj_type="0" tileset_id="BRF_tree01" layer_index="22" pos_x="-4405.91" pos_y="598.2521" offset_z="0" arg_x="1" arg_y="1" arg_z="0" visible="1" is_locked="0" x_flip="0" obj_infos="" bind_tag="" control_info="" />
  <tile_obj obj_id="262724" obj_type="0" tileset_id="BRF_tree02" layer_index="22" pos_x="-4557.16943" pos_y="426.27063" offset_z="0" arg_x="1" arg_y="1" arg_z="0" visible="1" is_locked="0" x_flip="1" obj_infos="" bind_tag="" control_info="" />
  <tile_obj obj_id="262725" obj_type="0" tileset_id="BRF_tree02" layer_index="22" pos_x="-4607.614" pos_y="227.82608" offset_z="0" arg_x="1" arg_y="1" arg_z="0" visible="1" is_locked="0" x_flip="0" obj_infos="" bind_tag="" control_info="" />
  <tile_obj obj_id="262733" obj_type="0" tileset_id="BRF_yanti06" layer_index="36" pos_x="-3971.28027" pos_y="243.659149" offset_z="0" arg_x="1" arg_y="1" arg_z="0" visible="1" is_locked="0" x_flip="0" obj_infos="" bind_tag="" control_info="" />
  <tile_obj obj_id="262734" obj_type="0" tileset_id="BRF_yanti06" layer_index="36" pos_x="-3797.503" pos_y="226.881409" offset_z="0" arg_x="1" arg_y="1" arg_z="0" visible="1" is_locked="0" x_flip="0" obj_infos="" bind_tag="" control_info="" />
  <tile_obj obj_id="262735" obj_type="0" tileset_id="BRF_yanti02" layer_index="36" pos_x="-3639.16968" pos_y="260.214783" offset_z="0" arg_x="1" arg_y="1" arg_z="0" visible="1" is_locked="0" x_flip="1" obj_infos="" bind_tag="" control_info="" />
  <tile_obj obj_id="262736" obj_type="0" tileset_id="BRF_yanti04" layer_index="36" pos_x="-3645.83643" pos_y="383.548065" offset_z="0" arg_x="1" arg_y="1" arg_z="0" visible="1" is_locked="0" x_flip="1" obj_infos="" bind_tag="" control_info="" />
  <tile_obj obj_id="262739" obj_type="0" tileset_id="BRF_yanti04" layer_index="36" pos_x="-3587.2688" pos_y="566.753662" offset_z="0" arg_x="1" arg_y="1" arg_z="0" visible="1" is_locked="0" x_flip="1" obj_infos="" bind_tag="" control_info="" />
  <tile_obj obj_id="262740" obj_type="0" tileset_id="BRF_yanti02" layer_index="36" pos_x="-3581.60229" pos_y="447.309" offset_z="0" arg_x="1" arg_y="1" arg_z="0" visible="1" is_locked="0" x_flip="1" obj_infos="" bind_tag="" control_info="" />
  <tile_obj obj_id="262745" obj_type="0" tileset_id="BRF_yanti03" layer_index="36" pos_x="-4034.05933" pos_y="588.7709" offset_z="0" arg_x="1" arg_y="1" arg_z="0" visible="1" is_locked="0" x_flip="0" obj_infos="" bind_tag="" control_info="" />
  <tile_obj obj_id="262750" obj_type="0" tileset_id="BRF_yanti04" layer_index="36" pos_x="-4332.614" pos_y="503.4372" offset_z="0" arg_x="1" arg_y="1" arg_z="0" visible="1" is_locked="0" x_flip="0" obj_infos="" bind_tag="" control_info="" />
  <tile_obj obj_id="262751" obj_type="0" tileset_id="BRF_yanti01" layer_index="36" pos_x="-4330.614" pos_y="387.104034" offset_z="0" arg_x="1" arg_y="1" arg_z="0" visible="1" is_locked="0" x_flip="0" obj_infos="" bind_tag="" control_info="" />
  <tile_obj obj_id="262763" obj_type="0" tileset_id="BRF_rock06" layer_index="23" pos_x="-4245.3916" pos_y="486.326233" offset_z="0" arg_x="1" arg_y="1" arg_z="0" visible="1" is_locked="0" x_flip="0" obj_infos="" bind_tag="" control_info="" />
  <tile_obj obj_id="262764" obj_type="0" tileset_id="BRF_rock06" layer_index="23" pos_x="-4073.16943" pos_y="417.437378" offset_z="0" arg_x="1" arg_y="1" arg_z="0" visible="1" is_locked="0" x_flip="0" obj_infos="" bind_tag="" control_info="" />
  <tile_obj obj_id="262765" obj_type="0" tileset_id="BRF_rock06" layer_index="23" pos_x="-3860.94727" pos_y="371.8818" offset_z="0" arg_x="1" arg_y="1" arg_z="0" visible="1" is_locked="0" x_flip="0" obj_infos="" bind_tag="" control_info="" />
  <tile_obj obj_id="262766" obj_type="0" tileset_id="BRF_rock04" layer_index="23" pos_x="-3799.83618" pos_y="291.215118" offset_z="0" arg_x="1" arg_y="1" arg_z="0" visible="1" is_locked="0" x_flip="0" obj_infos="" bind_tag="" control_info="" />
  <tile_obj obj_id="262813" obj_type="0" tileset_id="BRF_tree01" layer_index="22" pos_x="-4322.503" pos_y="420.7707" offset_z="0" arg_x="1" arg_y="1" arg_z="0" visible="1" is_locked="0" x_flip="0" obj_infos="" bind_tag="" control_info="" />
  <tile_obj obj_id="264154" obj_type="0" tileset_id="BRF_tree08" layer_index="22" pos_x="-3517.61548" pos_y="442.547821" offset_z="0" arg_x="1" arg_y="1" arg_z="0" visible="1" is_locked="0" x_flip="0" obj_infos="" bind_tag="" control_info="" />
  <tile_obj obj_id="264155" obj_type="0" tileset_id="BRF_tree09" layer_index="22" pos_x="-3549.83765" pos_y="346.214447" offset_z="0" arg_x="1" arg_y="1" arg_z="0" visible="1" is_locked="0" x_flip="0" obj_infos="" bind_tag="" control_info="" />
  <tile_obj obj_id="264159" obj_type="0" tileset_id="BRF_tree09" layer_index="22" pos_x="-3799.39331" pos_y="183.7701" offset_z="0" arg_x="1" arg_y="1" arg_z="0" visible="1" is_locked="0" x_flip="1" obj_infos="" bind_tag="" control_info="" />
  <tile_obj obj_id="264160" obj_type="0" tileset_id="BRF_tree08" layer_index="22" pos_x="-3553.838" pos_y="14.547821" offset_z="0" arg_x="1" arg_y="1" arg_z="0" visible="1" is_locked="0" x_flip="0" obj_infos="" bind_tag="" control_info="" />
  <tile_obj obj_id="264161" obj_type="0" tileset_id="BRF_yanti04" layer_index="36" pos_x="-4053.39038" pos_y="215.880844" offset_z="0" arg_x="1" arg_y="1" arg_z="0" visible="1" is_locked="0" x_flip="1" obj_infos="" bind_tag="" control_info="" />
  <tile_obj obj_id="264162" obj_type="0" tileset_id="BRF_yanti02" layer_index="36" pos_x="-4047.167" pos_y="91.4363556" offset_z="0" arg_x="1" arg_y="1" arg_z="0" visible="1" is_locked="0" x_flip="1" obj_infos="" bind_tag="" control_info="" />
  <tile_obj obj_id="264163" obj_type="0" tileset_id="BRF_yanti01" layer_index="36" pos_x="-4164.05762" pos_y="23.1030273" offset_z="0" arg_x="1" arg_y="1" arg_z="0" visible="1" is_locked="0" x_flip="1" obj_infos="" bind_tag="" control_info="" />
  <tile_obj obj_id="264164" obj_type="0" tileset_id="BRF_yanti06" layer_index="36" pos_x="-4336.28" pos_y="-5.23028564" offset_z="0" arg_x="1" arg_y="1" arg_z="0" visible="1" is_locked="0" x_flip="0" obj_infos="" bind_tag="" control_info="" />
  <tile_obj obj_id="264165" obj_type="0" tileset_id="BRF_yanti01" layer_index="36" pos_x="-4498.502" pos_y="29.7697144" offset_z="0" arg_x="1" arg_y="1" arg_z="0" visible="1" is_locked="0" x_flip="0" obj_infos="" bind_tag="" control_info="" />
  <tile_obj obj_id="264166" obj_type="0" tileset_id="BRF_yanti05" layer_index="36" pos_x="-4507.39063" pos_y="160.325287" offset_z="0" arg_x="1" arg_y="1" arg_z="0" visible="1" is_locked="0" x_flip="0" obj_infos="" bind_tag="" control_info="" />
  <tile_obj obj_id="264167" obj_type="0" tileset_id="BRF_yanti04" layer_index="36" pos_x="-4240.724" pos_y="336.9919" offset_z="0" arg_x="1" arg_y="1" arg_z="0" visible="1" is_locked="0" x_flip="0" obj_infos="" bind_tag="" control_info="" />
  <tile_obj obj_id="264168" obj_type="0" tileset_id="BRF_yanti07" layer_index="36" pos_x="-4349.61328" pos_y="251.43634" offset_z="0" arg_x="1.2" arg_y="1.2" arg_z="20" visible="1" is_locked="0" x_flip="0" obj_infos="" bind_tag="" control_info="" />
  <tile_obj obj_id="264169" obj_type="0" tileset_id="BRF_tree02" layer_index="22" pos_x="-4383.613" pos_y="425.380859" offset_z="0" arg_x="1" arg_y="1" arg_z="0" visible="1" is_locked="0" x_flip="0" obj_infos="" bind_tag="" control_info="" />
  <tile_obj obj_id="264170" obj_type="0" tileset_id="BRF_tree03" layer_index="22" pos_x="-4435.835" pos_y="370.7697" offset_z="0" arg_x="1" arg_y="1" arg_z="0" visible="1" is_locked="0" x_flip="0" obj_infos="" bind_tag="" control_info="" />
  <tile_obj obj_id="264171" obj_type="0" tileset_id="BRF_corrupted" layer_index="31" pos_x="-4448.05762" pos_y="295.214172" offset_z="0" arg_x="1" arg_y="1" arg_z="0" visible="1" is_locked="0" x_flip="0" obj_infos="" bind_tag="" control_info="" />
  <tile_obj obj_id="264172" obj_type="0" tileset_id="BRF_grass02" layer_index="31" pos_x="-4383.613" pos_y="296.325256" offset_z="0" arg_x="1" arg_y="1" arg_z="0" visible="1" is_locked="0" x_flip="0" obj_infos="" bind_tag="" control_info="" />
  <tile_obj obj_id="264173" obj_type="0" tileset_id="BRF_grass02" layer_index="31" pos_x="-3845.50024" pos_y="112.695755" offset_z="0" arg_x="1" arg_y="1" arg_z="0" visible="1" is_locked="0" x_flip="0" obj_infos="" bind_tag="" control_info="" />
  <tile_obj obj_id="264174" obj_type="0" tileset_id="BRF_grass02" layer_index="31" pos_x="-3541.64868" pos_y="331.362427" offset_z="0" arg_x="1" arg_y="1" arg_z="0" visible="1" is_locked="0" x_flip="0" obj_infos="" bind_tag="" control_info="" />
  <tile_obj obj_id="264175" obj_type="0" tileset_id="BRF_grass02" layer_index="31" pos_x="-3599.87085" pos_y="-50.11908" offset_z="0" arg_x="1" arg_y="1" arg_z="0" visible="1" is_locked="0" x_flip="0" obj_infos="" bind_tag="" control_info="" />
  <tile_obj obj_id="264176" obj_type="0" tileset_id="BRF_grass01" layer_index="22" pos_x="-3817.79688" pos_y="98.69574" offset_z="0" arg_x="1" arg_y="1" arg_z="0" visible="1" is_locked="0" x_flip="0" obj_infos="" bind_tag="" control_info="" />
  <tile_obj obj_id="264177" obj_type="0" tileset_id="BRF_grass01" layer_index="22" pos_x="-3916.31543" pos_y="123.140175" offset_z="0" arg_x="1" arg_y="1" arg_z="0" visible="1" is_locked="0" x_flip="0" obj_infos="" bind_tag="" control_info="" />
  <tile_obj obj_id="264178" obj_type="0" tileset_id="BRF_grass01" layer_index="22" pos_x="-3617.05615" pos_y="-42.04499" offset_z="0" arg_x="1" arg_y="1" arg_z="0" visible="1" is_locked="0" x_flip="0" obj_infos="" bind_tag="" control_info="" />
  <tile_obj obj_id="264181" obj_type="0" tileset_id="BRF_tree05" layer_index="22" pos_x="-3599.87085" pos_y="-6.85980225" offset_z="0" arg_x="1" arg_y="1" arg_z="0" visible="1" is_locked="0" x_flip="0" obj_infos="" bind_tag="" control_info="" />
  <tile_obj obj_id="264182" obj_type="0" tileset_id="BRF_tree06" layer_index="22" pos_x="-3755.42651" pos_y="156.103134" offset_z="0" arg_x="1" arg_y="1" arg_z="0" visible="1" is_locked="0" x_flip="0" obj_infos="" bind_tag="" control_info="" />
  <tile_obj obj_id="264183" obj_type="0" tileset_id="BRF_tree07" layer_index="22" pos_x="-3946.5376" pos_y="102.806854" offset_z="0" arg_x="1" arg_y="1" arg_z="0" visible="1" is_locked="0" x_flip="0" obj_infos="" bind_tag="" control_info="" />
  <tile_obj obj_id="264187" obj_type="0" tileset_id="BRF_tree09" layer_index="22" pos_x="-3881.42725" pos_y="122.584679" offset_z="0" arg_x="1" arg_y="1" arg_z="0" visible="1" is_locked="0" x_flip="0" obj_infos="" bind_tag="" control_info="" />
  <tile_obj obj_id="264188" obj_type="0" tileset_id="BRF_tree09" layer_index="22" pos_x="-4169.723" pos_y="-71.63754" offset_z="0" arg_x="1" arg_y="1" arg_z="0" visible="1" is_locked="0" x_flip="0" obj_infos="" bind_tag="" control_info="" />
  <tile_obj obj_id="264189" obj_type="0" tileset_id="BRF_tree09" layer_index="22" pos_x="-3990.75952" pos_y="-347.044922" offset_z="0" arg_x="1" arg_y="1" arg_z="0" visible="1" is_locked="0" x_flip="0" obj_infos="" bind_tag="" control_info="" />
  <tile_obj obj_id="264190" obj_type="0" tileset_id="BRF_tree08" layer_index="22" pos_x="-3912.241" pos_y="-302.933838" offset_z="0" arg_x="1" arg_y="1" arg_z="0" visible="1" is_locked="0" x_flip="0" obj_infos="" bind_tag="" control_info="" />
  <tile_obj obj_id="264191" obj_type="0" tileset_id="BRF_tree08" layer_index="22" pos_x="-4226.31445" pos_y="-33.3041763" offset_z="0" arg_x="1" arg_y="1" arg_z="0" visible="1" is_locked="0" x_flip="0" obj_infos="" bind_tag="" control_info="" />
  <tile_obj obj_id="264192" obj_type="0" tileset_id="BRF_tree08" layer_index="22" pos_x="-4403.79639" pos_y="-257.8968" offset_z="0" arg_x="1" arg_y="1" arg_z="0" visible="1" is_locked="0" x_flip="1" obj_infos="" bind_tag="" control_info="" />
  <tile_obj obj_id="264193" obj_type="0" tileset_id="BRF_tree08" layer_index="22" pos_x="-4455.64941" pos_y="-22.2671051" offset_z="0" arg_x="1" arg_y="1" arg_z="0" visible="1" is_locked="0" x_flip="0" obj_infos="" bind_tag="" control_info="" />
  <tile_obj obj_id="264200" obj_type="0" tileset_id="BRF_corrupted" layer_index="31" pos_x="-4177.278" pos_y="-115.896942" offset_z="0" arg_x="1" arg_y="1" arg_z="0" visible="1" is_locked="0" x_flip="0" obj_infos="" bind_tag="" control_info="" />
  <tile_obj obj_id="264201" obj_type="0" tileset_id="BRF_corrupted" layer_index="31" pos_x="-4620.61133" pos_y="87.4363861" offset_z="0" arg_x="1" arg_y="1" arg_z="0" visible="1" is_locked="0" x_flip="0" obj_infos="" bind_tag="" control_info="" />
  <tile_obj obj_id="264202" obj_type="0" tileset_id="BRF_corrupted" layer_index="31" pos_x="-4610.61133" pos_y="-15.8968887" offset_z="0" arg_x="1" arg_y="1" arg_z="0" visible="1" is_locked="0" x_flip="0" obj_infos="" bind_tag="" control_info="" />
  <tile_obj obj_id="264203" obj_type="0" tileset_id="BRF_corrupted" layer_index="31" pos_x="-4480.61133" pos_y="-81.45248" offset_z="0" arg_x="1" arg_y="1" arg_z="0" visible="1" is_locked="0" x_flip="0" obj_infos="" bind_tag="" control_info="" />
  <tile_obj obj_id="264205" obj_type="0" tileset_id="BRF_corrupted" layer_index="31" pos_x="-4429.05566" pos_y="-323.896942" offset_z="0" arg_x="1" arg_y="1" arg_z="0" visible="1" is_locked="0" x_flip="0" obj_infos="" bind_tag="" control_info="" />
  <tile_obj obj_id="264206" obj_type="0" tileset_id="BRF_grass02" layer_index="31" pos_x="-3999.27783" pos_y="-414.785828" offset_z="0" arg_x="1" arg_y="1" arg_z="0" visible="1" is_locked="0" x_flip="0" obj_infos="" bind_tag="" control_info="" />
  <tile_obj obj_id="264207" obj_type="0" tileset_id="BRF_grass02" layer_index="31" pos_x="-4373.722" pos_y="-310.34137" offset_z="0" arg_x="1" arg_y="1" arg_z="0" visible="1" is_locked="0" x_flip="0" obj_infos="" bind_tag="" control_info="" />
  <tile_obj obj_id="264220" obj_type="0" tileset_id="BRF_grass01" layer_index="22" pos_x="-4375.94434" pos_y="-316.119141" offset_z="0" arg_x="1" arg_y="1" arg_z="0" visible="1" is_locked="0" x_flip="0" obj_infos="" bind_tag="" control_info="" />
  <tile_obj obj_id="264221" obj_type="0" tileset_id="BRF_grass01" layer_index="22" pos_x="-4011.05566" pos_y="-418.785828" offset_z="0" arg_x="1" arg_y="1" arg_z="0" visible="1" is_locked="0" x_flip="0" obj_infos="" bind_tag="" control_info="" />
  <tile_obj obj_id="264225" obj_type="0" tileset_id="BRF_rock02" layer_index="36" pos_x="-4337.722" pos_y="-141.8969" offset_z="0" arg_x="1" arg_y="1" arg_z="0" visible="1" is_locked="0" x_flip="0" obj_infos="" bind_tag="" control_info="" />
  <tile_obj obj_id="264226" obj_type="0" tileset_id="BRF_rock02" layer_index="36" pos_x="-4064.389" pos_y="-41.89691" offset_z="0" arg_x="1" arg_y="1" arg_z="0" visible="1" is_locked="0" x_flip="0" obj_infos="" bind_tag="" control_info="" />
  <tile_obj obj_id="264227" obj_type="0" tileset_id="BRF_rock02" layer_index="36" pos_x="-3788.8335" pos_y="-223.008041" offset_z="0" arg_x="1" arg_y="1" arg_z="0" visible="1" is_locked="0" x_flip="0" obj_infos="" bind_tag="" control_info="" />
  <tile_obj obj_id="264228" obj_type="0" tileset_id="BRF_rock02" layer_index="36" pos_x="-3715.5" pos_y="-139.674744" offset_z="0" arg_x="1" arg_y="1" arg_z="0" visible="1" is_locked="0" x_flip="0" obj_infos="" bind_tag="" control_info="" />
  <tile_obj obj_id="264229" obj_type="0" tileset_id="BRF_rock03" layer_index="36" pos_x="-3888.8335" pos_y="-369.674683" offset_z="0" arg_x="1" arg_y="1" arg_z="0" visible="1" is_locked="0" x_flip="0" obj_infos="" bind_tag="" control_info="" />
  <tile_obj obj_id="264230" obj_type="0" tileset_id="BRF_rock03" layer_index="36" pos_x="-3809.94434" pos_y="-237.452484" offset_z="0" arg_x="1" arg_y="1" arg_z="0" visible="1" is_locked="0" x_flip="0" obj_infos="" bind_tag="" control_info="" />
  <tile_obj obj_id="264232" obj_type="0" tileset_id="BRF_rock03" layer_index="36" pos_x="-4216.61133" pos_y="-410.785828" offset_z="0" arg_x="1" arg_y="1" arg_z="0" visible="1" is_locked="0" x_flip="0" obj_infos="" bind_tag="" control_info="" />
  <tile_obj obj_id="264233" obj_type="0" tileset_id="BRF_rock03" layer_index="36" pos_x="-4322.1665" pos_y="-325.230255" offset_z="0" arg_x="1" arg_y="1" arg_z="0" visible="1" is_locked="0" x_flip="0" obj_infos="" bind_tag="" control_info="" />
  <tile_obj obj_id="264234" obj_type="0" tileset_id="BRF_rock03" layer_index="36" pos_x="-4563.722" pos_y="-442.5636" offset_z="0" arg_x="1" arg_y="1" arg_z="0" visible="1" is_locked="0" x_flip="0" obj_infos="" bind_tag="" control_info="" />
  <tile_obj obj_id="264250" obj_type="0" tileset_id="20633" layer_index="31" pos_x="-4364.8335" pos_y="-415.896942" offset_z="0" arg_x="1" arg_y="1" arg_z="0" visible="1" is_locked="0" x_flip="0" obj_infos="" bind_tag="" control_info="" />
  <tile_obj obj_id="264251" obj_type="0" tileset_id="grass_BRF" layer_index="31" pos_x="-4089.27783" pos_y="-455.452484" offset_z="0" arg_x="1" arg_y="1" arg_z="0" visible="1" is_locked="0" x_flip="0" obj_infos="" bind_tag="" control_info="" />
  <tile_obj obj_id="264252" obj_type="0" tileset_id="4059" layer_index="23" pos_x="-4381.278" pos_y="-378.719147" offset_z="0" arg_x="1" arg_y="1" arg_z="0" visible="1" is_locked="0" x_flip="0" obj_infos="" bind_tag="" control_info="" />
  <tile_obj obj_id="264253" obj_type="0" tileset_id="4059" layer_index="23" pos_x="-3924.611" pos_y="-442.05246" offset_z="0" arg_x="1" arg_y="1" arg_z="0" visible="1" is_locked="0" x_flip="0" obj_infos="" bind_tag="" control_info="" />
  <tile_obj obj_id="264254" obj_type="0" tileset_id="4059" layer_index="23" pos_x="-4251.278" pos_y="-142.052475" offset_z="0" arg_x="1" arg_y="1" arg_z="0" visible="1" is_locked="0" x_flip="0" obj_infos="" bind_tag="" control_info="" />
  <tile_obj obj_id="264257" obj_type="0" tileset_id="4059" layer_index="23" pos_x="-3614.16675" pos_y="-75.83026" offset_z="0" arg_x="1" arg_y="1" arg_z="0" visible="1" is_locked="0" x_flip="0" obj_infos="" bind_tag="" control_info="" />
  <tile_obj obj_id="264262" obj_type="0" tileset_id="bg_ts_smjz_69" layer_index="27" pos_x="-4681.7666" pos_y="-249.674652" offset_z="0" arg_x="1" arg_y="1" arg_z="0" visible="1" is_locked="0" x_flip="0" obj_infos="" bind_tag="" control_info="" />
  <tile_obj obj_id="264264" obj_type="0" tileset_id="bg_ts_wujian_21" layer_index="27" pos_x="-4601.32227" pos_y="-207.952423" offset_z="0" arg_x="1" arg_y="1" arg_z="0" visible="1" is_locked="0" x_flip="0" obj_infos="" bind_tag="" control_info="" />
  <tile_obj obj_id="264265" obj_type="0" tileset_id="bg_ts_wujian_22" layer_index="27" pos_x="-4625.7666" pos_y="-440.785767" offset_z="0" arg_x="1" arg_y="1" arg_z="0" visible="1" is_locked="0" x_flip="0" obj_infos="" bind_tag="" control_info="" />
  <tile_obj obj_id="264268" obj_type="0" tileset_id="bg_ts_wujian_21" layer_index="27" pos_x="-4530.7666" pos_y="-205.7302" offset_z="0" arg_x="1" arg_y="1" arg_z="0" visible="1" is_locked="0" x_flip="1" obj_infos="" bind_tag="" control_info="" />
  <tile_obj obj_id="264269" obj_type="0" tileset_id="bg_ts_wujian_21" layer_index="27" pos_x="-4416.87842" pos_y="-263.508" offset_z="0" arg_x="1" arg_y="1" arg_z="0" visible="1" is_locked="0" x_flip="1" obj_infos="" bind_tag="" control_info="" />
  <tile_obj obj_id="264270" obj_type="0" tileset_id="bg_ts_wujian_21" layer_index="27" pos_x="-4435.7666" pos_y="-343.508" offset_z="0" arg_x="1" arg_y="1" arg_z="0" visible="1" is_locked="0" x_flip="0" obj_infos="" bind_tag="" control_info="" />
  <tile_obj obj_id="264273" obj_type="0" tileset_id="bg_ts_wujian_18" layer_index="27" pos_x="-4624.32227" pos_y="-271.5635" offset_z="0" arg_x="1" arg_y="1" arg_z="0" visible="1" is_locked="0" x_flip="0" obj_infos="" bind_tag="" control_info="" />
  <tile_obj obj_id="264274" obj_type="0" tileset_id="bg_ts_wujian_18" layer_index="27" pos_x="-4609.656" pos_y="-260.3413" offset_z="0" arg_x="1" arg_y="1" arg_z="0" visible="1" is_locked="0" x_flip="0" obj_infos="" bind_tag="" control_info="" />
  <tile_obj obj_id="267049" obj_type="0" tileset_id="leitai" layer_index="26" pos_x="-4482.151" pos_y="-272.628235" offset_z="0" arg_x="1" arg_y="1" arg_z="0" visible="1" is_locked="0" x_flip="0" obj_infos="" bind_tag="" control_info="" />
  <tile_obj obj_id="269840" obj_type="0" tileset_id="BRF_tree07" layer_index="26" pos_x="-4575.911" pos_y="26.75924" offset_z="0" arg_x="1" arg_y="1" arg_z="0" visible="1" is_locked="0" x_flip="0" obj_infos="" bind_tag="" control_info="" />
  <tile_obj obj_id="269841" obj_type="0" tileset_id="BRF_tree07" layer_index="26" pos_x="-4575.195" pos_y="317.704041" offset_z="0" arg_x="1" arg_y="1" arg_z="0" visible="1" is_locked="0" x_flip="0" obj_infos="" bind_tag="" control_info="" />
  <tile_obj obj_id="269842" obj_type="0" tileset_id="BRF_tree05" layer_index="26" pos_x="-4622.97266" pos_y="302.703979" offset_z="0" arg_x="1" arg_y="1" arg_z="0" visible="1" is_locked="0" x_flip="0" obj_infos="" bind_tag="" control_info="" />
  <tile_obj obj_id="269843" obj_type="0" tileset_id="BRF_tree05" layer_index="26" pos_x="-4541.86133" pos_y="332.703979" offset_z="0" arg_x="1" arg_y="1" arg_z="0" visible="1" is_locked="0" x_flip="0" obj_infos="" bind_tag="" control_info="" />
  <tile_obj obj_id="269844" obj_type="0" tileset_id="BRF_tree07" layer_index="26" pos_x="-4486.30566" pos_y="343.259583" offset_z="0" arg_x="1" arg_y="1" arg_z="0" visible="1" is_locked="0" x_flip="0" obj_infos="" bind_tag="" control_info="" />
  <tile_obj obj_id="269845" obj_type="0" tileset_id="BRF_tree06" layer_index="26" pos_x="-4462.97266" pos_y="359.370667" offset_z="0" arg_x="1" arg_y="1" arg_z="0" visible="1" is_locked="0" x_flip="0" obj_infos="" bind_tag="" control_info="" />
  <tile_obj obj_id="269846" obj_type="0" tileset_id="BRF_tree05" layer_index="26" pos_x="-4426.82129" pos_y="391.977325" offset_z="0" arg_x="1" arg_y="1" arg_z="0" visible="1" is_locked="0" x_flip="0" obj_infos="" bind_tag="" control_info="" />
  <tile_obj obj_id="269839" obj_type="0" tileset_id="BRF_tree05" layer_index="26" pos_x="-4631.467" pos_y="16.2036362" offset_z="0" arg_x="1" arg_y="1" arg_z="0" visible="1" is_locked="0" x_flip="0" obj_infos="" bind_tag="" control_info="" />
  <tile_areas area_id="1175" bind_info_type="12" center_map_x="-3679.16553" center_map_y="-957.49646" width="100" height="200" rotate="0" aabb_state="1" aabb_min_x="-1545" aabb_min_y="-1660.5" aabb_max_x="779" aabb_max_y="677.5">
    <pts_info>-519,-515;-666,-993;-1065,-1742;-1254,-2075;-1340,-2211;-1447,-2453;-1507,-2647;-1540,-2908;-927,-3131;-229,-3134;160,-3216;428,-3311;595,-3292;706,-3012;701,-2797;635,-2351;514,-2035;340,-1782;356,-1618;277,-1423;92,-1091;94,-406;189,-141;223,121;571,570;774,915;662,1140;590,1247;517,1345;387,1228;220,1076;259,979;163,892;93,921;64,879;98,768</pts_info>
    <properties>
      <property name="control_id" value="" />
      <property name="init_state" value="0" />
      <property name="collide_type" value="0" />
    </properties>
  </tile_areas>
  <tile_areas area_id="999" bind_info_type="12" center_map_x="-3965.771" center_map_y="1037.0271" width="100" height="200" rotate="0" aabb_state="1" aabb_min_x="-621" aabb_min_y="-688.5" aabb_max_x="551" aabb_max_y="545.5">
    <pts_info>-314,-1196;-199,-1367;-167,-1301;-221,-1158;-5,-896;95,-972;461,-477;377,-442;367,-349;407,-275;528,-315;546,-230;444,-166;410,307;308,638;355,797;231,820;213,953;127,1060;-19,1081;-146,997;-170,835;-402,711;-457,319;-394,195;-431,-294;-321,-465;-584,-630;-615,-810;-616,-1027</pts_info>
    <properties>
      <property name="control_id" value="" />
      <property name="init_state" value="0" />
      <property name="collide_type" value="0" />
    </properties>
  </tile_areas>
  <tile_areas area_id="1061" bind_info_type="12" center_map_x="-4493.46045" center_map_y="-538.5192" width="100" height="200" rotate="0" aabb_state="1" aabb_min_x="-139" aabb_min_y="-77.5" aabb_max_x="117" aabb_max_y="72.5">
    <pts_info>-134,60;89,-145;112,-68;-74,135</pts_info>
    <properties>
      <property name="control_id" value="" />
      <property name="init_state" value="0" />
      <property name="collide_type" value="0" />
    </properties>
  </tile_areas>
  <tile_areas area_id="1251" bind_info_type="12" center_map_x="-3961.86523" center_map_y="-764.8181" width="100" height="200" rotate="0" aabb_state="1" aabb_min_x="-62" aabb_min_y="-62" aabb_max_x="66" aabb_max_y="43.5">
    <pts_info>-23,-114;61,5;28,77;-57,-48</pts_info>
    <properties>
      <property name="control_id" value="" />
      <property name="init_state" value="0" />
      <property name="collide_type" value="0" />
    </properties>
  </tile_areas>
  <tile_areas area_id="1405" bind_info_type="12" center_map_x="-4577.5127" center_map_y="499.4981" width="100" height="200" rotate="0" aabb_state="1" aabb_min_x="-160.446289" aabb_min_y="-284.1357" aabb_max_x="330" aabb_max_y="149.5">
    <pts_info>-139,-555;-71,-558;32,-490;265,-309;325,77;217,278;154,289;63,164;-64,86;-155,-319</pts_info>
    <properties>
      <property name="control_id" value="" />
      <property name="init_state" value="0" />
      <property name="collide_type" value="0" />
    </properties>
  </tile_areas>
</blend_map_tileinfo>